notation/__init__.py
notation/notation.py
notation-0.0.3.dist-info/LICENSE
notation-0.0.3.dist-info/METADATA
notation-0.0.3.dist-info/WHEEL
notation-0.0.3.dist-info/top_level.txt
notation-0.0.3.dist-info/RECORD
