Metadata-Version: 2.1
Name: notation
Version: 0.0.3
Summary: Notation is a decorator for annotating Python functions.
Author-email: Adam Patterson <adam@faranalytics.net>
Project-URL: Homepage, https://github.com/faranalytics/python_notation
Project-URL: Bug Tracker, https://github.com/faranalytics/python_notation/issues
Classifier: Programming Language :: Python :: 3
Classifier: License :: OSI Approved :: MIT License
Classifier: Operating System :: OS Independent
Requires-Python: >=3.8
License-File: LICENSE
